{
  "version": "2.0",
  "pipeline_stage": "validated",
  "title": "EmoEEG-MC: A Multi-Context Emotional EEG Dataset for Cross-Context Emotion Decoding",
  "description": "EmoEEG-MC is a multi-context emotional EEG dataset comprising 64-channel EEG and peripheral physiological recordings from 60 participants exposed to video-induced and imagery-induced emotional stimuli across seven emotion categories (joy, inspiration, tenderness, fear, disgust, sadness, and neutral). This dataset addresses the critical gap in cross-context emotion decoding by enabling investigation of neural mechanisms underlying emotional processing across different elicitation contexts, with demonstrated cross-context classification accuracies of 66.7% for binary emotion classification and 28.9% for seven-category emotion classification using machine learning approaches.",
  "methods_description": "EEG data were collected from 60 participants using 64-channel EEG systems along with peripheral physiological measurements (PPG and GSR) for a subset of participants. Participants were exposed to two distinct emotional induction contexts: video-based stimuli and mental imagery tasks. Each context included 21 trials spanning seven emotional categories (joy, inspiration, tenderness, fear, disgust, sadness, and neutral). Emotional experiences were validated through subjective self-report measures.",
  "license": "CC0",
  "dataset_type": "raw",
  "authors": {
    "Xin XU": {},
    "Xinke SHEN": {},
    "Xuyang CHEN": {},
    "Qingzhu ZHANG": {},
    "Sitian WANG": {},
    "Yihan LI": {},
    "Zongsheng LI": {},
    "Dan ZHANG": {
      "orcid": "0000-0002-7592-3200"
    },
    "Mingming ZHANG": {},
    "Quanying LIU": {}
  },
  "keywords": [
    {
      "term": "EEG"
    },
    {
      "term": "emotion recognition"
    },
    {
      "term": "cross-context emotion decoding"
    },
    {
      "term": "affective computing"
    },
    {
      "term": "electroencephalography"
    },
    {
      "term": "emotional states"
    },
    {
      "term": "machine learning classification"
    }
  ],
  "related_identifiers": [
    {
      "identifier": "https://github.com/nemarDatasets/on005540",
      "identifier_type": "URL",
      "relation_type": "IsDescribedBy"
    },
    {
      "identifier": "https://nemar.org/dataset/on005540",
      "identifier_type": "URL",
      "relation_type": "IsDescribedBy"
    },
    {
      "identifier": "10.1038/s41597-023-02650-w",
      "identifier_type": "DOI",
      "relation_type": "References"
    },
    {
      "identifier": "10.1073/pnas.1321664111",
      "identifier_type": "DOI",
      "relation_type": "References"
    },
    {
      "identifier": "10.18112/openneuro.ds005540.v1.0.7",
      "identifier_type": "DOI",
      "relation_type": "IsDerivedFrom"
    }
  ],
  "funding_references": [
    {
      "funder_name": "SUSTech Undergraduate Innovation and Entrepreneurship Training Program(2024S07)"
    },
    {
      "funder_name": "National Key R&D Program of China",
      "award_number": "2021YFF1200804"
    },
    {
      "funder_name": "Shenzhen Excellent Youth Project",
      "award_number": "RCYX20231211090405003"
    },
    {
      "funder_name": "Shenzhen Science and Technology Innovation Committee",
      "award_number": "RCBS20231211090748082"
    },
    {
      "funder_name": "Shenzhen Science and Technology Innovation Committee",
      "award_number": "KJZD20230923115221044"
    },
    {
      "funder_name": "Shenzhen Science and Technology Innovation Committee",
      "award_number": "KCXFZ20201221173400001"
    }
  ],
  "resource_type_general": "Dataset",
  "resource_type_specific": "Neuroimaging Dataset",
  "modalities": [
    "beh",
    "eeg"
  ],
  "sizes": [
    "75.6 GB (1077 files)"
  ],
  "formats": [
    ".4593",
    ".csv",
    ".edf",
    ".gz",
    ".ipynb",
    ".json",
    ".mat",
    ".md",
    ".npy",
    ".pth",
    ".py",
    ".pyc",
    ".tsv",
    ".txt",
    ".xlsx",
    ".yml"
  ],
  "source_hash": "af17f4085375b44bf367ae2633f9f5a1175a4e55dfbfe862c99bc8a75f4d7cc2"
}